tendem_mcp/__init__.py
tendem_mcp/client.py
tendem_mcp/models.py
tendem_mcp/server.py
tendem_mcp-0.1.3.dist-info/METADATA
tendem_mcp-0.1.3.dist-info/WHEEL
tendem_mcp-0.1.3.dist-info/entry_points.txt
tendem_mcp-0.1.3.dist-info/licenses/LICENSE
tendem_mcp-0.1.3.dist-info/RECORD
