Metadata-Version: 2.4
Name: tendem-mcp
Version: 0.1.3
Summary: MCP server for Tendem task management API
Project-URL: Homepage, https://tendem.ai
Project-URL: Repository, https://github.com/toloka/tendem-mcp
Author: alexdrydew
License-Expression: Apache-2.0
License-File: LICENSE
Keywords: ai,mcp,task-management,tendem
Classifier: Development Status :: 3 - Alpha
Classifier: Intended Audience :: Developers
Classifier: License :: OSI Approved :: Apache Software License
Classifier: Programming Language :: Python :: 3.13
Requires-Python: <3.14,>=3.13
Requires-Dist: fastmcp>=2.0
Requires-Dist: httpx>=0.28
Requires-Dist: pydantic>=2.0
